multiple_permissions/__init__.py
multiple_permissions/middlewares.py
multiple_permissions/permissions.py
multiple_permissions/tests.py
multiple_permissions-0.2.2.dist-info/LICENCE
multiple_permissions-0.2.2.dist-info/METADATA
multiple_permissions-0.2.2.dist-info/WHEEL
multiple_permissions-0.2.2.dist-info/top_level.txt
multiple_permissions-0.2.2.dist-info/RECORD
