Metadata-Version: 2.1
Name: multiple-permissions
Version: 0.2.2
Summary: Use multiple permission classes in django class based views.
Home-page: https://github.com/aram2726/django_multiple_permissions
Author: Aram Haroyan
Author-email: aramharoyan@gmail.com
License: MIT
Keywords: django multiple permissions use many permission python rest framework
Platform: UNKNOWN
Classifier: Environment :: Web Environment
Classifier: Framework :: Django
Classifier: Intended Audience :: Developers
Classifier: License :: OSI Approved :: MIT License
Classifier: Operating System :: OS Independent
Classifier: Programming Language :: Python
Classifier: Programming Language :: Python :: 3
Classifier: Programming Language :: Python :: 3.6
Classifier: Programming Language :: Python :: 3.7
Classifier: Programming Language :: Python :: 3.8
Classifier: Topic :: Internet :: WWW/HTTP
Classifier: Topic :: Internet :: WWW/HTTP :: Dynamic Content
